setup.cfg
setup.py
formlib/basehandlers.py
formlibHGMMP.egg-info/PKG-INFO
formlibHGMMP.egg-info/SOURCES.txt
formlibHGMMP.egg-info/dependency_links.txt
formlibHGMMP.egg-info/not-zip-safe
formlibHGMMP.egg-info/requires.txt
formlibHGMMP.egg-info/top_level.txt