Metadata-Version: 1.0
Name: formlibHGMMP
Version: 0.0.1
Summary: Some form widgets, not really chipper
Home-page: https://github.com/MartinPeschke/formlib
Author: Martin Peschke
Author-email: martin@per-4.com
License: BSD
Platform: UNKNOWN
